[
    {
        "kind": "youtube#video",
        "etag": "_72YWm_9f98mzZ8oSx4M2Mrkx4E",
        "id": "XVU1WvebNdI",
        "snippet": {
            "publishedAt": "2016-07-23T23:04:41Z",
            "channelId": "UCuWeBHxVe6C69JTBpiY-Y8Q",
            "title": "Suicide Squad - Official Comic-Con Soundtrack Remix [HD] | REACCION | Juanito Say",
            "description": "EPICO ultimo trailer de Suicide Squad presentado en la San Diego Comic Con, \u00a1mira mi reaccion!\n\n\u2591\u2591\u2591\u2591\u2591\u2591\u2591\u2591\u2591\u2591\u2591\u2591\u2591\u2591\u2591\u2591\u2591\u2591\u2591\u2591\u2591\u2591\u2591\u2591\u2591\u2591\u2591\u2591\u2591\u2591\u2591\u2591\u2591\u2591\u2591\u2591\u2591\u2591\n\n\u2605 SUSCRIBETE A MI CANAL Y SE UN FRIKI DELCARAJO: http://www.youtube.com/user/juanitosay?sub_confirmation=1\n\n\u25baTIENDA DELCARAJO \u27a5 http://goo.gl/Noz7Yu\n\n\u25ba Sigueme en:\nTwitter \u27a5 http://twitter.com/juanitosay\nFacebook \u27a5 http://facebook.com/juanitosayoficial\nFacebook Personal \u27a5 http://facebook.com/soyjuanitosay\nYounow \u27a5 http://younow.com/JuanitoSay\nFreak Show \u27a5 http://freakshowtv.com.ar\n\n\u25ba Contacto prensa: say@freakshowtv.com.ar\n\n\u25ba DESCARGA MI APP PARA CHROME Y FIREFOX: http://myapp.wips.com/delcarajo-teve-juanito-say-extension\n\n\u25ba Agradecimientos: Belunita (produccion y asistente multiusos), Chelo Irrazabal (dibujos e intro animada estilo Dragon Ball), Flematico (dibujos).",
            "thumbnails": {
                "default": {
                    "url": "https://i.ytimg.com/vi/XVU1WvebNdI/default.jpg",
                    "width": 120,
                    "height": 90
                },
                "medium": {
                    "url": "https://i.ytimg.com/vi/XVU1WvebNdI/mqdefault.jpg",
                    "width": 320,
                    "height": 180
                },
                "high": {
                    "url": "https://i.ytimg.com/vi/XVU1WvebNdI/hqdefault.jpg",
                    "width": 480,
                    "height": 360
                },
                "standard": {
                    "url": "https://i.ytimg.com/vi/XVU1WvebNdI/sddefault.jpg",
                    "width": 640,
                    "height": 480
                },
                "maxres": {
                    "url": "https://i.ytimg.com/vi/XVU1WvebNdI/maxresdefault.jpg",
                    "width": 1280,
                    "height": 720
                }
            },
            "channelTitle": "DELCARAJO TV",
            "tags": [
                "juanito say",
                "delcarajo",
                "suicide squad",
                "suicide squad trailer",
                "suicide squad comic con",
                "suicide squad soundtrack",
                "video reaccion",
                "suicide squad reaccion",
                "jared leto",
                "will smith",
                "suicide squad blitz",
                "suicide squad reaction",
                "batman trailer",
                "suicide squad batman",
                "suicide squad trailer 3",
                "margot robbie",
                "joker",
                "harley quinn",
                "suicide squad reaccion al trailer",
                "trailer"
            ],
            "categoryId": "24",
            "liveBroadcastContent": "none",
            "localized": {
                "title": "Suicide Squad - Official Comic-Con Soundtrack Remix [HD] | REACCION | Juanito Say",
                "description": "EPICO ultimo trailer de Suicide Squad presentado en la San Diego Comic Con, \u00a1mira mi reaccion!\n\n\u2591\u2591\u2591\u2591\u2591\u2591\u2591\u2591\u2591\u2591\u2591\u2591\u2591\u2591\u2591\u2591\u2591\u2591\u2591\u2591\u2591\u2591\u2591\u2591\u2591\u2591\u2591\u2591\u2591\u2591\u2591\u2591\u2591\u2591\u2591\u2591\u2591\u2591\n\n\u2605 SUSCRIBETE A MI CANAL Y SE UN FRIKI DELCARAJO: http://www.youtube.com/user/juanitosay?sub_confirmation=1\n\n\u25baTIENDA DELCARAJO \u27a5 http://goo.gl/Noz7Yu\n\n\u25ba Sigueme en:\nTwitter \u27a5 http://twitter.com/juanitosay\nFacebook \u27a5 http://facebook.com/juanitosayoficial\nFacebook Personal \u27a5 http://facebook.com/soyjuanitosay\nYounow \u27a5 http://younow.com/JuanitoSay\nFreak Show \u27a5 http://freakshowtv.com.ar\n\n\u25ba Contacto prensa: say@freakshowtv.com.ar\n\n\u25ba DESCARGA MI APP PARA CHROME Y FIREFOX: http://myapp.wips.com/delcarajo-teve-juanito-say-extension\n\n\u25ba Agradecimientos: Belunita (produccion y asistente multiusos), Chelo Irrazabal (dibujos e intro animada estilo Dragon Ball), Flematico (dibujos)."
            }
        },
        "contentDetails": {
            "duration": "PT4M29S",
            "dimension": "2d",
            "definition": "hd",
            "caption": "false",
            "licensedContent": false,
            "contentRating": {},
            "projection": "rectangular"
        },
        "status": {
            "uploadStatus": "processed",
            "privacyStatus": "public",
            "license": "youtube",
            "embeddable": true,
            "publicStatsViewable": true,
            "madeForKids": false
        },
        "statistics": {
            "viewCount": "7170",
            "likeCount": "244",
            "favoriteCount": "0",
            "commentCount": "36"
        }
    }
]