[{"id_str":"1107355169065484294","created_at":1552849020000,"full_text":"#AmberHeardIsAnAbuser That is all. https:\/\/t.co\/xm4Z669QN0","lang":"en","in_reply_to_status_id_str":null,"in_reply_to_user_id":null,"entities.hashtags":[{"indices":[0,21],"text":"AmberHeardIsAnAbuser"}],"entities.media":[{"original_info":{"width":498,"height":204},"display_url":"pic.twitter.com\/xm4Z669QN0","indices":[35,58],"sizes":{"small":{"w":498,"h":204,"resize":"fit"},"large":{"w":498,"h":204,"resize":"fit"},"thumb":{"w":150,"h":150,"resize":"crop"},"medium":{"w":498,"h":204,"resize":"fit"}},"id_str":"1107355162312626176","expanded_url":"https:\/\/twitter.com\/Yariene\/status\/1107355169065484294\/photo\/1","media_url_https":"https:\/\/pbs.twimg.com\/tweet_video_thumb\/D14dpzHW0AABM8O.jpg","id":1107355162312626176,"type":"photo","media_url":"http:\/\/pbs.twimg.com\/tweet_video_thumb\/D14dpzHW0AABM8O.jpg","url":"https:\/\/t.co\/xm4Z669QN0"}],"entities.symbols":[],"entities.urls":[],"entities.user_mentions":[],"source":"<a href=\"http:\/\/twitter.com\/#!\/download\/ipad\" rel=\"nofollow\">Twitter for iPad<\/a>","quoted_status.id_str":null,"quoted_status.created_at":null,"quoted_status.full_text":null,"quoted_status.lang":null,"quoted_status.in_reply_to_status_id_str":null,"quoted_status.in_reply_to_user_id":null,"quoted_status.entities.hashtags":null,"quoted_status.entities.media":null,"quoted_status.entities.symbols":null,"quoted_status.entities.urls":null,"quoted_status.entities.user_mentions":null,"quoted_status.user.id_str":null,"quoted_status.source":null,"user.id_str":"1915770480","user.created_at":1380417793000,"user.description":"Earthling \ud83c\udf0e","user.followers_count":83,"user.friends_count":800,"user.lang":null,"user.location":"\ud83c\uddf5\ud83c\uddf7\ud83c\uddfa\ud83c\uddf8","user.name":"Y\u039b\u042fI\u03a3\u041f\u03a3 \u271e\u2600\ufe0f\ud83c\udf0a\ud83d\udc9c","user.screen_name":"Yariene","user.profile_banner_url":"https:\/\/pbs.twimg.com\/profile_banners\/1915770480\/1617310531","user.profile_image_url":"http:\/\/pbs.twimg.com\/profile_images\/1382082432959135747\/TMmbjhDf_normal.jpg","user.statuses_count":9329,"user.url":null,"user.verified":false,"proc_text":"AmberHeardIsAnAbuser That is all https t co xm4Z669QN0","cluster":349},{"id_str":"1106407302238818304","created_at":1552623031000,"full_text":"@LOrealParisUSA Amber Heard has made L\u2019Oreal soooo unappealing.","lang":"en","in_reply_to_status_id_str":"1106314100576010240","in_reply_to_user_id":87222643.0,"entities.hashtags":[],"entities.media":null,"entities.symbols":[],"entities.urls":[],"entities.user_mentions":[{"indices":[0,15],"screen_name":"LOrealParisUSA","id_str":"87222643","name":"L'Or\u00e9al Paris USA","id":87222643}],"source":"<a href=\"http:\/\/twitter.com\/#!\/download\/ipad\" rel=\"nofollow\">Twitter for iPad<\/a>","quoted_status.id_str":null,"quoted_status.created_at":null,"quoted_status.full_text":null,"quoted_status.lang":null,"quoted_status.in_reply_to_status_id_str":null,"quoted_status.in_reply_to_user_id":null,"quoted_status.entities.hashtags":null,"quoted_status.entities.media":null,"quoted_status.entities.symbols":null,"quoted_status.entities.urls":null,"quoted_status.entities.user_mentions":null,"quoted_status.user.id_str":null,"quoted_status.source":null,"user.id_str":"1915770480","user.created_at":1380417793000,"user.description":"Earthling \ud83c\udf0e","user.followers_count":83,"user.friends_count":800,"user.lang":null,"user.location":"\ud83c\uddf5\ud83c\uddf7\ud83c\uddfa\ud83c\uddf8","user.name":"Y\u039b\u042fI\u03a3\u041f\u03a3 \u271e\u2600\ufe0f\ud83c\udf0a\ud83d\udc9c","user.screen_name":"Yariene","user.profile_banner_url":"https:\/\/pbs.twimg.com\/profile_banners\/1915770480\/1617310531","user.profile_image_url":"http:\/\/pbs.twimg.com\/profile_images\/1382082432959135747\/TMmbjhDf_normal.jpg","user.statuses_count":9329,"user.url":null,"user.verified":false,"proc_text":"LOrealParisUSA Amber Heard has made L Oreal soooo unappealing","cluster":-1},{"id_str":"1106659935025356800","created_at":1552683263000,"full_text":"Johnny Depp\u2019s deposition against Amber Heard.\n\n https:\/\/t.co\/uxk76oZCHM","lang":"en","in_reply_to_status_id_str":null,"in_reply_to_user_id":null,"entities.hashtags":[],"entities.media":null,"entities.symbols":[],"entities.urls":[{"display_url":"courthousenews.com\/wp-content\/upl\u2026","indices":[48,71],"expanded_url":"https:\/\/www.courthousenews.com\/wp-content\/uploads\/2019\/03\/DeppHeard.pdf","url":"https:\/\/t.co\/uxk76oZCHM"}],"entities.user_mentions":[],"source":"<a href=\"http:\/\/twitter.com\/#!\/download\/ipad\" rel=\"nofollow\">Twitter for iPad<\/a>","quoted_status.id_str":null,"quoted_status.created_at":null,"quoted_status.full_text":null,"quoted_status.lang":null,"quoted_status.in_reply_to_status_id_str":null,"quoted_status.in_reply_to_user_id":null,"quoted_status.entities.hashtags":null,"quoted_status.entities.media":null,"quoted_status.entities.symbols":null,"quoted_status.entities.urls":null,"quoted_status.entities.user_mentions":null,"quoted_status.user.id_str":null,"quoted_status.source":null,"user.id_str":"1915770480","user.created_at":1380417793000,"user.description":"Earthling \ud83c\udf0e","user.followers_count":83,"user.friends_count":800,"user.lang":null,"user.location":"\ud83c\uddf5\ud83c\uddf7\ud83c\uddfa\ud83c\uddf8","user.name":"Y\u039b\u042fI\u03a3\u041f\u03a3 \u271e\u2600\ufe0f\ud83c\udf0a\ud83d\udc9c","user.screen_name":"Yariene","user.profile_banner_url":"https:\/\/pbs.twimg.com\/profile_banners\/1915770480\/1617310531","user.profile_image_url":"http:\/\/pbs.twimg.com\/profile_images\/1382082432959135747\/TMmbjhDf_normal.jpg","user.statuses_count":9329,"user.url":null,"user.verified":false,"proc_text":"Johnny Depp s deposition against Amber Heard https t co uxk76oZCHM","cluster":-1},{"id_str":"1105554459885740032","created_at":1552419698000,"full_text":"i wanna know why this amber heard and johnny depp shit is all of the sudden trending today? seems completely random.","lang":"en","in_reply_to_status_id_str":null,"in_reply_to_user_id":null,"entities.hashtags":[],"entities.media":null,"entities.symbols":[],"entities.urls":[],"entities.user_mentions":[],"source":"<a href=\"http:\/\/twitter.com\/download\/iphone\" rel=\"nofollow\">Twitter for iPhone<\/a>","quoted_status.id_str":null,"quoted_status.created_at":null,"quoted_status.full_text":null,"quoted_status.lang":null,"quoted_status.in_reply_to_status_id_str":null,"quoted_status.in_reply_to_user_id":null,"quoted_status.entities.hashtags":null,"quoted_status.entities.media":null,"quoted_status.entities.symbols":null,"quoted_status.entities.urls":null,"quoted_status.entities.user_mentions":null,"quoted_status.user.id_str":null,"quoted_status.source":null,"user.id_str":"54268633","user.created_at":1246900793000,"user.description":"i cry over scottish princes and old hollywood boys \ud83c\udf9e | she | hers | rip kc \ud83d\udc3e","user.followers_count":1266,"user.friends_count":260,"user.lang":null,"user.location":"The X Files Basement ","user.name":"alex \ud83c\udf9e\ud83d\udc95","user.screen_name":"james_mcavoys","user.profile_banner_url":"https:\/\/pbs.twimg.com\/profile_banners\/54268633\/1567110002","user.profile_image_url":"http:\/\/pbs.twimg.com\/profile_images\/1382736108321173506\/-icuTQSd_normal.jpg","user.statuses_count":58914,"user.url":"https:\/\/t.co\/ObIHFPVTZD","user.verified":false,"proc_text":"i wanna know why this amber heard and johnny depp shit is all of the sudden trending today seems completely random","cluster":859},{"id_str":"1105546407207821312","created_at":1552417778000,"full_text":"What is this new information about Johnny Depp and Amber Heard?","lang":"en","in_reply_to_status_id_str":null,"in_reply_to_user_id":null,"entities.hashtags":[],"entities.media":null,"entities.symbols":[],"entities.urls":[],"entities.user_mentions":[],"source":"<a href=\"http:\/\/twitter.com\/download\/android\" rel=\"nofollow\">Twitter for Android<\/a>","quoted_status.id_str":null,"quoted_status.created_at":null,"quoted_status.full_text":null,"quoted_status.lang":null,"quoted_status.in_reply_to_status_id_str":null,"quoted_status.in_reply_to_user_id":null,"quoted_status.entities.hashtags":null,"quoted_status.entities.media":null,"quoted_status.entities.symbols":null,"quoted_status.entities.urls":null,"quoted_status.entities.user_mentions":null,"quoted_status.user.id_str":null,"quoted_status.source":null,"user.id_str":"2277440502","user.created_at":1388917895000,"user.description":"22 \u2741 \u2648\ufe0e \u2741 \ud835\udc6a\ud835\udc7a\ud835\udc7c\ud835\udc6d '22 \ud80c\udcf0","user.followers_count":267,"user.friends_count":177,"user.lang":null,"user.location":"she\/her\ud83d\udc97","user.name":"\ud835\udc1b\ud835\udc2b\ud835\udc22 \ud83e\udd8b","user.screen_name":"thegoddessbrii","user.profile_banner_url":"https:\/\/pbs.twimg.com\/profile_banners\/2277440502\/1611156097","user.profile_image_url":"http:\/\/pbs.twimg.com\/profile_images\/1352663475533746177\/o5wOp3bb_normal.jpg","user.statuses_count":28690,"user.url":"https:\/\/t.co\/DviGpn8Fun","user.verified":false,"proc_text":"What is this new information about Johnny Depp and Amber Heard","cluster":859},{"id_str":"1105509842448515073","created_at":1552409060000,"full_text":"yikes can\u2019t believe i supported amber heard","lang":"en","in_reply_to_status_id_str":null,"in_reply_to_user_id":null,"entities.hashtags":[],"entities.media":null,"entities.symbols":[],"entities.urls":[],"entities.user_mentions":[],"source":"<a href=\"http:\/\/twitter.com\/download\/iphone\" rel=\"nofollow\">Twitter for iPhone<\/a>","quoted_status.id_str":null,"quoted_status.created_at":null,"quoted_status.full_text":null,"quoted_status.lang":null,"quoted_status.in_reply_to_status_id_str":null,"quoted_status.in_reply_to_user_id":null,"quoted_status.entities.hashtags":null,"quoted_status.entities.media":null,"quoted_status.entities.symbols":null,"quoted_status.entities.urls":null,"quoted_status.entities.user_mentions":null,"quoted_status.user.id_str":null,"quoted_status.source":null,"user.id_str":"2455149315","user.created_at":1396449538000,"user.description":"21 | \u235f\u20dd | i can do this all day | fan account #blacklivesmatter #stopasianhate | she\/her","user.followers_count":1209,"user.friends_count":694,"user.lang":null,"user.location":"","user.name":"sava | fatws spoilers","user.screen_name":"wcrthysteve","user.profile_banner_url":"https:\/\/pbs.twimg.com\/profile_banners\/2455149315\/1586148371","user.profile_image_url":"http:\/\/pbs.twimg.com\/profile_images\/1247022767494627329\/Yw_4ustg_normal.jpg","user.statuses_count":31301,"user.url":"https:\/\/t.co\/wOxNI0XIda","user.verified":false,"proc_text":"yikes can t believe i supported amber heard","cluster":-1},{"id_str":"1105526218596724736","created_at":1552412964000,"full_text":"wtf is happening with amber heard and johnny depp now......","lang":"en","in_reply_to_status_id_str":null,"in_reply_to_user_id":null,"entities.hashtags":[],"entities.media":null,"entities.symbols":[],"entities.urls":[],"entities.user_mentions":[],"source":"<a href=\"http:\/\/twitter.com\/download\/iphone\" rel=\"nofollow\">Twitter for iPhone<\/a>","quoted_status.id_str":null,"quoted_status.created_at":null,"quoted_status.full_text":null,"quoted_status.lang":null,"quoted_status.in_reply_to_status_id_str":null,"quoted_status.in_reply_to_user_id":null,"quoted_status.entities.hashtags":null,"quoted_status.entities.media":null,"quoted_status.entities.symbols":null,"quoted_status.entities.urls":null,"quoted_status.entities.user_mentions":null,"quoted_status.user.id_str":null,"quoted_status.source":null,"user.id_str":"838865127227154434","user.created_at":1488836006000,"user.description":"wanda maximoff supremacy","user.followers_count":370,"user.friends_count":67,"user.lang":null,"user.location":"Westview","user.name":"cami.","user.screen_name":"scarlettwitched","user.profile_banner_url":"https:\/\/pbs.twimg.com\/profile_banners\/838865127227154434\/1613261682","user.profile_image_url":"http:\/\/pbs.twimg.com\/profile_images\/1368747480813248512\/Tf2DQjPH_normal.jpg","user.statuses_count":43489,"user.url":"https:\/\/t.co\/erJ6I8VTJS","user.verified":false,"proc_text":"wtf is happening with amber heard and johnny depp now","cluster":859},{"id_str":"1105488965610565632","created_at":1552404083000,"full_text":"What the fuck is going on today? Amber Heard and Johnny Depp?","lang":"en","in_reply_to_status_id_str":null,"in_reply_to_user_id":null,"entities.hashtags":[],"entities.media":null,"entities.symbols":[],"entities.urls":[],"entities.user_mentions":[],"source":"<a href=\"http:\/\/twitter.com\/download\/android\" rel=\"nofollow\">Twitter for Android<\/a>","quoted_status.id_str":null,"quoted_status.created_at":null,"quoted_status.full_text":null,"quoted_status.lang":null,"quoted_status.in_reply_to_status_id_str":null,"quoted_status.in_reply_to_user_id":null,"quoted_status.entities.hashtags":null,"quoted_status.entities.media":null,"quoted_status.entities.symbols":null,"quoted_status.entities.urls":null,"quoted_status.entities.user_mentions":null,"quoted_status.user.id_str":null,"quoted_status.source":null,"user.id_str":"1050782707398062081","user.created_at":1539361094000,"user.description":"waiting for her grand return","user.followers_count":233,"user.friends_count":729,"user.lang":null,"user.location":"","user.name":"Wendy is 2m \ud83d\udc99","user.screen_name":"butterfliesWan","user.profile_banner_url":"https:\/\/pbs.twimg.com\/profile_banners\/1050782707398062081\/1577279806","user.profile_image_url":"http:\/\/pbs.twimg.com\/profile_images\/1312805527940927491\/F_dz7_D4_normal.jpg","user.statuses_count":37687,"user.url":null,"user.verified":false,"proc_text":"What the fuck is going on today Amber Heard and Johnny Depp","cluster":859},{"id_str":"1105487588582928385","created_at":1552403754000,"full_text":"what the FUCK is going on with johnny depp and amber heard uhh","lang":"en","in_reply_to_status_id_str":null,"in_reply_to_user_id":null,"entities.hashtags":[],"entities.media":null,"entities.symbols":[],"entities.urls":[],"entities.user_mentions":[],"source":"<a href=\"http:\/\/twitter.com\/download\/iphone\" rel=\"nofollow\">Twitter for iPhone<\/a>","quoted_status.id_str":null,"quoted_status.created_at":null,"quoted_status.full_text":null,"quoted_status.lang":null,"quoted_status.in_reply_to_status_id_str":null,"quoted_status.in_reply_to_user_id":null,"quoted_status.entities.hashtags":null,"quoted_status.entities.media":null,"quoted_status.entities.symbols":null,"quoted_status.entities.urls":null,"quoted_status.entities.user_mentions":null,"quoted_status.user.id_str":null,"quoted_status.source":null,"user.id_str":"2455149315","user.created_at":1396449538000,"user.description":"21 | \u235f\u20dd | i can do this all day | fan account #blacklivesmatter #stopasianhate | she\/her","user.followers_count":1209,"user.friends_count":694,"user.lang":null,"user.location":"","user.name":"sava | fatws spoilers","user.screen_name":"wcrthysteve","user.profile_banner_url":"https:\/\/pbs.twimg.com\/profile_banners\/2455149315\/1586148371","user.profile_image_url":"http:\/\/pbs.twimg.com\/profile_images\/1247022767494627329\/Yw_4ustg_normal.jpg","user.statuses_count":31301,"user.url":"https:\/\/t.co\/wOxNI0XIda","user.verified":false,"proc_text":"what the FUCK is going on with johnny depp and amber heard uhh","cluster":859},{"id_str":"1105684015745515520","created_at":1552450586000,"full_text":"@TMZ Why aren\u2019t TMZ talking about Johnny Depp being abused by Amber Heard?","lang":"en","in_reply_to_status_id_str":"1105683669686149120","in_reply_to_user_id":16331010.0,"entities.hashtags":[],"entities.media":null,"entities.symbols":[],"entities.urls":[],"entities.user_mentions":[{"indices":[0,4],"screen_name":"TMZ","id_str":"16331010","name":"TMZ","id":16331010}],"source":"<a href=\"http:\/\/twitter.com\/#!\/download\/ipad\" rel=\"nofollow\">Twitter for iPad<\/a>","quoted_status.id_str":null,"quoted_status.created_at":null,"quoted_status.full_text":null,"quoted_status.lang":null,"quoted_status.in_reply_to_status_id_str":null,"quoted_status.in_reply_to_user_id":null,"quoted_status.entities.hashtags":null,"quoted_status.entities.media":null,"quoted_status.entities.symbols":null,"quoted_status.entities.urls":null,"quoted_status.entities.user_mentions":null,"quoted_status.user.id_str":null,"quoted_status.source":null,"user.id_str":"1915770480","user.created_at":1380417793000,"user.description":"Earthling \ud83c\udf0e","user.followers_count":83,"user.friends_count":800,"user.lang":null,"user.location":"\ud83c\uddf5\ud83c\uddf7\ud83c\uddfa\ud83c\uddf8","user.name":"Y\u039b\u042fI\u03a3\u041f\u03a3 \u271e\u2600\ufe0f\ud83c\udf0a\ud83d\udc9c","user.screen_name":"Yariene","user.profile_banner_url":"https:\/\/pbs.twimg.com\/profile_banners\/1915770480\/1617310531","user.profile_image_url":"http:\/\/pbs.twimg.com\/profile_images\/1382082432959135747\/TMmbjhDf_normal.jpg","user.statuses_count":9329,"user.url":null,"user.verified":false,"proc_text":"TMZ Why aren t TMZ talking about Johnny Depp being abused by Amber Heard","cluster":-1},{"id_str":"1105853508316745728","created_at":1552490996000,"full_text":"@iTunes Amber Heard puts me off this movie.","lang":"en","in_reply_to_status_id_str":"1103028678756261888","in_reply_to_user_id":66515223.0,"entities.hashtags":[],"entities.media":null,"entities.symbols":[],"entities.urls":[],"entities.user_mentions":[{"indices":[0,7],"screen_name":"iTunes","id_str":"66515223","name":"iTunes","id":66515223}],"source":"<a href=\"http:\/\/twitter.com\/#!\/download\/ipad\" rel=\"nofollow\">Twitter for iPad<\/a>","quoted_status.id_str":null,"quoted_status.created_at":null,"quoted_status.full_text":null,"quoted_status.lang":null,"quoted_status.in_reply_to_status_id_str":null,"quoted_status.in_reply_to_user_id":null,"quoted_status.entities.hashtags":null,"quoted_status.entities.media":null,"quoted_status.entities.symbols":null,"quoted_status.entities.urls":null,"quoted_status.entities.user_mentions":null,"quoted_status.user.id_str":null,"quoted_status.source":null,"user.id_str":"1915770480","user.created_at":1380417793000,"user.description":"Earthling \ud83c\udf0e","user.followers_count":83,"user.friends_count":800,"user.lang":null,"user.location":"\ud83c\uddf5\ud83c\uddf7\ud83c\uddfa\ud83c\uddf8","user.name":"Y\u039b\u042fI\u03a3\u041f\u03a3 \u271e\u2600\ufe0f\ud83c\udf0a\ud83d\udc9c","user.screen_name":"Yariene","user.profile_banner_url":"https:\/\/pbs.twimg.com\/profile_banners\/1915770480\/1617310531","user.profile_image_url":"http:\/\/pbs.twimg.com\/profile_images\/1382082432959135747\/TMmbjhDf_normal.jpg","user.statuses_count":9329,"user.url":null,"user.verified":false,"proc_text":"iTunes Amber Heard puts me off this movie","cluster":-1},{"id_str":"1105642260966854657","created_at":1552440631000,"full_text":"where y\u2019all get your amber heard and johnny depp sources from ?","lang":"en","in_reply_to_status_id_str":null,"in_reply_to_user_id":null,"entities.hashtags":[],"entities.media":null,"entities.symbols":[],"entities.urls":[],"entities.user_mentions":[],"source":"<a href=\"http:\/\/twitter.com\/download\/iphone\" rel=\"nofollow\">Twitter for iPhone<\/a>","quoted_status.id_str":null,"quoted_status.created_at":null,"quoted_status.full_text":null,"quoted_status.lang":null,"quoted_status.in_reply_to_status_id_str":null,"quoted_status.in_reply_to_user_id":null,"quoted_status.entities.hashtags":null,"quoted_status.entities.media":null,"quoted_status.entities.symbols":null,"quoted_status.entities.urls":null,"quoted_status.entities.user_mentions":null,"quoted_status.user.id_str":null,"quoted_status.source":null,"user.id_str":"1048985795804254208","user.created_at":1538932677000,"user.description":"GRAMMY WINNER HARRY STYLES","user.followers_count":492,"user.friends_count":515,"user.lang":null,"user.location":"any pronouns | 20","user.name":"izzy","user.screen_name":"dontworryharlin","user.profile_banner_url":"https:\/\/pbs.twimg.com\/profile_banners\/1048985795804254208\/1616631281","user.profile_image_url":"http:\/\/pbs.twimg.com\/profile_images\/1383129487857086465\/kgf6DNUU_normal.jpg","user.statuses_count":33440,"user.url":"https:\/\/t.co\/1Rt3ctH8GZ","user.verified":false,"proc_text":"where y all get your amber heard and johnny depp sources from","cluster":859},{"id_str":"1105828326910971906","created_at":1552484993000,"full_text":"@tmz talks about everybody but are suddenly quiet about Johnny Depp and Amber Heard. I wonder why. https:\/\/t.co\/YbBDjHo2Ay","lang":"en","in_reply_to_status_id_str":null,"in_reply_to_user_id":16331010.0,"entities.hashtags":[],"entities.media":[{"original_info":{"width":498,"height":396},"display_url":"pic.twitter.com\/YbBDjHo2Ay","indices":[99,122],"sizes":{"small":{"w":498,"h":396,"resize":"fit"},"large":{"w":498,"h":396,"resize":"fit"},"thumb":{"w":150,"h":150,"resize":"crop"},"medium":{"w":498,"h":396,"resize":"fit"}},"id_str":"1105828304991518720","expanded_url":"https:\/\/twitter.com\/Yariene\/status\/1105828326910971906\/photo\/1","media_url_https":"https:\/\/pbs.twimg.com\/tweet_video_thumb\/D1iw_AWXgAAU_b7.jpg","id":1105828304991518720,"type":"photo","media_url":"http:\/\/pbs.twimg.com\/tweet_video_thumb\/D1iw_AWXgAAU_b7.jpg","url":"https:\/\/t.co\/YbBDjHo2Ay"}],"entities.symbols":[],"entities.urls":[],"entities.user_mentions":[{"indices":[0,4],"screen_name":"TMZ","id_str":"16331010","name":"TMZ","id":16331010}],"source":"<a href=\"http:\/\/twitter.com\/download\/android\" rel=\"nofollow\">Twitter for Android<\/a>","quoted_status.id_str":null,"quoted_status.created_at":null,"quoted_status.full_text":null,"quoted_status.lang":null,"quoted_status.in_reply_to_status_id_str":null,"quoted_status.in_reply_to_user_id":null,"quoted_status.entities.hashtags":null,"quoted_status.entities.media":null,"quoted_status.entities.symbols":null,"quoted_status.entities.urls":null,"quoted_status.entities.user_mentions":null,"quoted_status.user.id_str":null,"quoted_status.source":null,"user.id_str":"1915770480","user.created_at":1380417793000,"user.description":"Earthling \ud83c\udf0e","user.followers_count":83,"user.friends_count":800,"user.lang":null,"user.location":"\ud83c\uddf5\ud83c\uddf7\ud83c\uddfa\ud83c\uddf8","user.name":"Y\u039b\u042fI\u03a3\u041f\u03a3 \u271e\u2600\ufe0f\ud83c\udf0a\ud83d\udc9c","user.screen_name":"Yariene","user.profile_banner_url":"https:\/\/pbs.twimg.com\/profile_banners\/1915770480\/1617310531","user.profile_image_url":"http:\/\/pbs.twimg.com\/profile_images\/1382082432959135747\/TMmbjhDf_normal.jpg","user.statuses_count":9329,"user.url":null,"user.verified":false,"proc_text":"tmz talks about everybody but are suddenly quiet about Johnny Depp and Amber Heard I wonder why https t co YbBDjHo2Ay","cluster":-1},{"id_str":"1105827202162151427","created_at":1552484724000,"full_text":"@aquamanmovie Amber Heard you should replace her. She is an abuser.","lang":"en","in_reply_to_status_id_str":"1104081600671711233","in_reply_to_user_id":8.591748642e+17,"entities.hashtags":[],"entities.media":null,"entities.symbols":[],"entities.urls":[],"entities.user_mentions":[{"indices":[0,13],"screen_name":"aquamanmovie","id_str":"859174864220938241","name":"Aquaman Movie","id":859174864220938241}],"source":"<a href=\"http:\/\/twitter.com\/download\/android\" rel=\"nofollow\">Twitter for Android<\/a>","quoted_status.id_str":null,"quoted_status.created_at":null,"quoted_status.full_text":null,"quoted_status.lang":null,"quoted_status.in_reply_to_status_id_str":null,"quoted_status.in_reply_to_user_id":null,"quoted_status.entities.hashtags":null,"quoted_status.entities.media":null,"quoted_status.entities.symbols":null,"quoted_status.entities.urls":null,"quoted_status.entities.user_mentions":null,"quoted_status.user.id_str":null,"quoted_status.source":null,"user.id_str":"1915770480","user.created_at":1380417793000,"user.description":"Earthling \ud83c\udf0e","user.followers_count":83,"user.friends_count":800,"user.lang":null,"user.location":"\ud83c\uddf5\ud83c\uddf7\ud83c\uddfa\ud83c\uddf8","user.name":"Y\u039b\u042fI\u03a3\u041f\u03a3 \u271e\u2600\ufe0f\ud83c\udf0a\ud83d\udc9c","user.screen_name":"Yariene","user.profile_banner_url":"https:\/\/pbs.twimg.com\/profile_banners\/1915770480\/1617310531","user.profile_image_url":"http:\/\/pbs.twimg.com\/profile_images\/1382082432959135747\/TMmbjhDf_normal.jpg","user.statuses_count":9329,"user.url":null,"user.verified":false,"proc_text":"aquamanmovie Amber Heard you should replace her She is an abuser","cluster":-1},{"id_str":"1105825241052389377","created_at":1552484257000,"full_text":"@enews The article about Johnny Depp and Amber Heard, where is it?","lang":"en","in_reply_to_status_id_str":"1105823619282808833","in_reply_to_user_id":2883841.0,"entities.hashtags":[],"entities.media":null,"entities.symbols":[],"entities.urls":[],"entities.user_mentions":[{"indices":[0,6],"screen_name":"enews","id_str":"2883841","name":"E! News","id":2883841}],"source":"<a href=\"http:\/\/twitter.com\/download\/android\" rel=\"nofollow\">Twitter for Android<\/a>","quoted_status.id_str":null,"quoted_status.created_at":null,"quoted_status.full_text":null,"quoted_status.lang":null,"quoted_status.in_reply_to_status_id_str":null,"quoted_status.in_reply_to_user_id":null,"quoted_status.entities.hashtags":null,"quoted_status.entities.media":null,"quoted_status.entities.symbols":null,"quoted_status.entities.urls":null,"quoted_status.entities.user_mentions":null,"quoted_status.user.id_str":null,"quoted_status.source":null,"user.id_str":"1915770480","user.created_at":1380417793000,"user.description":"Earthling \ud83c\udf0e","user.followers_count":83,"user.friends_count":800,"user.lang":null,"user.location":"\ud83c\uddf5\ud83c\uddf7\ud83c\uddfa\ud83c\uddf8","user.name":"Y\u039b\u042fI\u03a3\u041f\u03a3 \u271e\u2600\ufe0f\ud83c\udf0a\ud83d\udc9c","user.screen_name":"Yariene","user.profile_banner_url":"https:\/\/pbs.twimg.com\/profile_banners\/1915770480\/1617310531","user.profile_image_url":"http:\/\/pbs.twimg.com\/profile_images\/1382082432959135747\/TMmbjhDf_normal.jpg","user.statuses_count":9329,"user.url":null,"user.verified":false,"proc_text":"enews The article about Johnny Depp and Amber Heard where is it","cluster":859},{"id_str":"1105824821647163393","created_at":1552484157000,"full_text":"@TMZ The article about Johnny Depp and Amber Heard; where is it?","lang":"en","in_reply_to_status_id_str":"1105823380748619778","in_reply_to_user_id":16331010.0,"entities.hashtags":[],"entities.media":null,"entities.symbols":[],"entities.urls":[],"entities.user_mentions":[{"indices":[0,4],"screen_name":"TMZ","id_str":"16331010","name":"TMZ","id":16331010}],"source":"<a href=\"http:\/\/twitter.com\/download\/android\" rel=\"nofollow\">Twitter for Android<\/a>","quoted_status.id_str":null,"quoted_status.created_at":null,"quoted_status.full_text":null,"quoted_status.lang":null,"quoted_status.in_reply_to_status_id_str":null,"quoted_status.in_reply_to_user_id":null,"quoted_status.entities.hashtags":null,"quoted_status.entities.media":null,"quoted_status.entities.symbols":null,"quoted_status.entities.urls":null,"quoted_status.entities.user_mentions":null,"quoted_status.user.id_str":null,"quoted_status.source":null,"user.id_str":"1915770480","user.created_at":1380417793000,"user.description":"Earthling \ud83c\udf0e","user.followers_count":83,"user.friends_count":800,"user.lang":null,"user.location":"\ud83c\uddf5\ud83c\uddf7\ud83c\uddfa\ud83c\uddf8","user.name":"Y\u039b\u042fI\u03a3\u041f\u03a3 \u271e\u2600\ufe0f\ud83c\udf0a\ud83d\udc9c","user.screen_name":"Yariene","user.profile_banner_url":"https:\/\/pbs.twimg.com\/profile_banners\/1915770480\/1617310531","user.profile_image_url":"http:\/\/pbs.twimg.com\/profile_images\/1382082432959135747\/TMmbjhDf_normal.jpg","user.statuses_count":9329,"user.url":null,"user.verified":false,"proc_text":"TMZ The article about Johnny Depp and Amber Heard where is it","cluster":-1},{"id_str":"1105787963936399360","created_at":1552475369000,"full_text":"HELLO WHATS WITH ALL THIS JOHNNY DEPP AND AMBER HEARD ISSUE SKSKSKS","lang":"en","in_reply_to_status_id_str":null,"in_reply_to_user_id":null,"entities.hashtags":[],"entities.media":null,"entities.symbols":[],"entities.urls":[],"entities.user_mentions":[],"source":"<a href=\"http:\/\/twitter.com\/download\/android\" rel=\"nofollow\">Twitter for Android<\/a>","quoted_status.id_str":null,"quoted_status.created_at":null,"quoted_status.full_text":null,"quoted_status.lang":null,"quoted_status.in_reply_to_status_id_str":null,"quoted_status.in_reply_to_user_id":null,"quoted_status.entities.hashtags":null,"quoted_status.entities.media":null,"quoted_status.entities.symbols":null,"quoted_status.entities.urls":null,"quoted_status.entities.user_mentions":null,"quoted_status.user.id_str":null,"quoted_status.source":null,"user.id_str":"992992898265169920","user.created_at":1525582930000,"user.description":"7 for 7 \u2022 she\/her","user.followers_count":5852,"user.friends_count":4153,"user.lang":null,"user.location":"avengers compound ","user.name":"rye!","user.screen_name":"purelysteve","user.profile_banner_url":"https:\/\/pbs.twimg.com\/profile_banners\/992992898265169920\/1575293728","user.profile_image_url":"http:\/\/pbs.twimg.com\/profile_images\/1288048674195378177\/S3AiJK2__normal.jpg","user.statuses_count":10814,"user.url":"https:\/\/t.co\/IvGCRURhzQ","user.verified":false,"proc_text":"HELLO WHATS WITH ALL THIS JOHNNY DEPP AND AMBER HEARD ISSUE SKSKSKS","cluster":859},{"id_str":"1105808129583992832","created_at":1552480177000,"full_text":"@MeTooMVMT @TaranaBurke @ava @SpeakerPelosi @MargaretAtwood @VH1 What are your thoughts on the new chapter of the Johnny Depp\/Amber Heard saga?","lang":"en","in_reply_to_status_id_str":"1104039991297146883","in_reply_to_user_id":9.209059498e+17,"entities.hashtags":[],"entities.media":null,"entities.symbols":[],"entities.urls":[],"entities.user_mentions":[{"indices":[0,10],"screen_name":"MeTooMVMT","id_str":"920905949795246080","name":"me too.","id":920905949795246080},{"indices":[11,23],"screen_name":"TaranaBurke","id_str":"16863340","name":"Tarana","id":16863340},{"indices":[24,28],"screen_name":"ava","id_str":"14982804","name":"Ava DuVernay","id":14982804},{"indices":[29,43],"screen_name":"SpeakerPelosi","id_str":"15764644","name":"Nancy Pelosi","id":15764644},{"indices":[44,59],"screen_name":"MargaretAtwood","id_str":"54730258","name":"Margaret E. Atwood","id":54730258},{"indices":[60,64],"screen_name":"VH1","id_str":"33549858","name":"VH1","id":33549858}],"source":"<a href=\"http:\/\/twitter.com\/download\/android\" rel=\"nofollow\">Twitter for Android<\/a>","quoted_status.id_str":null,"quoted_status.created_at":null,"quoted_status.full_text":null,"quoted_status.lang":null,"quoted_status.in_reply_to_status_id_str":null,"quoted_status.in_reply_to_user_id":null,"quoted_status.entities.hashtags":null,"quoted_status.entities.media":null,"quoted_status.entities.symbols":null,"quoted_status.entities.urls":null,"quoted_status.entities.user_mentions":null,"quoted_status.user.id_str":null,"quoted_status.source":null,"user.id_str":"1915770480","user.created_at":1380417793000,"user.description":"Earthling \ud83c\udf0e","user.followers_count":83,"user.friends_count":800,"user.lang":null,"user.location":"\ud83c\uddf5\ud83c\uddf7\ud83c\uddfa\ud83c\uddf8","user.name":"Y\u039b\u042fI\u03a3\u041f\u03a3 \u271e\u2600\ufe0f\ud83c\udf0a\ud83d\udc9c","user.screen_name":"Yariene","user.profile_banner_url":"https:\/\/pbs.twimg.com\/profile_banners\/1915770480\/1617310531","user.profile_image_url":"http:\/\/pbs.twimg.com\/profile_images\/1382082432959135747\/TMmbjhDf_normal.jpg","user.statuses_count":9329,"user.url":null,"user.verified":false,"proc_text":"MeTooMVMT TaranaBurke ava SpeakerPelosi MargaretAtwood VH1 What are your thoughts on the new chapter of the Johnny Depp Amber Heard saga","cluster":-1},{"id_str":"1105801742636113920","created_at":1552478654000,"full_text":"What's happening in the Johnny Depp and Amber Heard case?","lang":"en","in_reply_to_status_id_str":null,"in_reply_to_user_id":null,"entities.hashtags":[],"entities.media":null,"entities.symbols":[],"entities.urls":[],"entities.user_mentions":[],"source":"<a href=\"http:\/\/twitter.com\" rel=\"nofollow\">Twitter Web Client<\/a>","quoted_status.id_str":null,"quoted_status.created_at":null,"quoted_status.full_text":null,"quoted_status.lang":null,"quoted_status.in_reply_to_status_id_str":null,"quoted_status.in_reply_to_user_id":null,"quoted_status.entities.hashtags":null,"quoted_status.entities.media":null,"quoted_status.entities.symbols":null,"quoted_status.entities.urls":null,"quoted_status.entities.user_mentions":null,"quoted_status.user.id_str":null,"quoted_status.source":null,"user.id_str":"129184424","user.created_at":1270299795000,"user.description":"Face of Panache","user.followers_count":22559,"user.friends_count":761,"user.lang":null,"user.location":"Mumbai","user.name":"Shreemi Verma","user.screen_name":"shreemiverma","user.profile_banner_url":"https:\/\/pbs.twimg.com\/profile_banners\/129184424\/1618857940","user.profile_image_url":"http:\/\/pbs.twimg.com\/profile_images\/1380049666490867712\/-iHBUL4N_normal.jpg","user.statuses_count":64928,"user.url":null,"user.verified":true,"proc_text":"What s happening in the Johnny Depp and Amber Heard case","cluster":859},{"id_str":"1106234168927813633","created_at":1552581753000,"full_text":"@MeTooMVMT @TaranaBurke @ava @SpeakerPelosi @MargaretAtwood @VH1 So, are you going to give your thoughts on Amber Heard lying?","lang":"en","in_reply_to_status_id_str":"1104039991297146883","in_reply_to_user_id":9.209059498e+17,"entities.hashtags":[],"entities.media":null,"entities.symbols":[],"entities.urls":[],"entities.user_mentions":[{"indices":[0,10],"screen_name":"MeTooMVMT","id_str":"920905949795246080","name":"me too.","id":920905949795246080},{"indices":[11,23],"screen_name":"TaranaBurke","id_str":"16863340","name":"Tarana","id":16863340},{"indices":[24,28],"screen_name":"ava","id_str":"14982804","name":"Ava DuVernay","id":14982804},{"indices":[29,43],"screen_name":"SpeakerPelosi","id_str":"15764644","name":"Nancy Pelosi","id":15764644},{"indices":[44,59],"screen_name":"MargaretAtwood","id_str":"54730258","name":"Margaret E. Atwood","id":54730258},{"indices":[60,64],"screen_name":"VH1","id_str":"33549858","name":"VH1","id":33549858}],"source":"<a href=\"http:\/\/twitter.com\/download\/android\" rel=\"nofollow\">Twitter for Android<\/a>","quoted_status.id_str":null,"quoted_status.created_at":null,"quoted_status.full_text":null,"quoted_status.lang":null,"quoted_status.in_reply_to_status_id_str":null,"quoted_status.in_reply_to_user_id":null,"quoted_status.entities.hashtags":null,"quoted_status.entities.media":null,"quoted_status.entities.symbols":null,"quoted_status.entities.urls":null,"quoted_status.entities.user_mentions":null,"quoted_status.user.id_str":null,"quoted_status.source":null,"user.id_str":"1915770480","user.created_at":1380417793000,"user.description":"Earthling \ud83c\udf0e","user.followers_count":83,"user.friends_count":800,"user.lang":null,"user.location":"\ud83c\uddf5\ud83c\uddf7\ud83c\uddfa\ud83c\uddf8","user.name":"Y\u039b\u042fI\u03a3\u041f\u03a3 \u271e\u2600\ufe0f\ud83c\udf0a\ud83d\udc9c","user.screen_name":"Yariene","user.profile_banner_url":"https:\/\/pbs.twimg.com\/profile_banners\/1915770480\/1617310531","user.profile_image_url":"http:\/\/pbs.twimg.com\/profile_images\/1382082432959135747\/TMmbjhDf_normal.jpg","user.statuses_count":9329,"user.url":null,"user.verified":false,"proc_text":"MeTooMVMT TaranaBurke ava SpeakerPelosi MargaretAtwood VH1 So are you going to give your thoughts on Amber Heard lying","cluster":-1}]