[
    {
        "kind": "youtube#video",
        "etag": "b-pa01-6fl7erzAuX_6foXU98Yg",
        "id": "wK3rDswPjWM",
        "snippet": {
            "publishedAt": "2021-05-30T16:56:15Z",
            "channelId": "UCZJ8Vxj-MdzcTQ8I5yQfujg",
            "title": "\u00bfQui\u00e9n MAT\u00d3 a MISSY BEVERS? REAL | EssarRock",
            "description": "Missy Bevers era instructora de fitness, alguien a quien todos amaban. Sin embargo, una ma\u00f1ana, mientras se preparaba para la clase, fue acosada y atacada. \u00bfQui\u00e9n podr\u00eda haber hecho tal cosa? Ve\u00e1moslo.\n\nSI TE GUST\u00d3 EL V\u00cdDEO NO OLVIDES APOYAR AL CANAL DEJANDO TU LIKE Y SUSCRIBIENDO, PARA AS\u00cd PODER SUBIR M\u00c1S CONTENIDO.\n\nSuscr\u00edbete\u25bahttps://www.youtube.com/channel/UCZJ8Vxj-MdzcTQ8I5yQfujg\n\n#MissyBevers #Fitness #RandyBevers",
            "thumbnails": {
                "default": {
                    "url": "https://i.ytimg.com/vi/wK3rDswPjWM/default.jpg",
                    "width": 120,
                    "height": 90
                },
                "medium": {
                    "url": "https://i.ytimg.com/vi/wK3rDswPjWM/mqdefault.jpg",
                    "width": 320,
                    "height": 180
                },
                "high": {
                    "url": "https://i.ytimg.com/vi/wK3rDswPjWM/hqdefault.jpg",
                    "width": 480,
                    "height": 360
                },
                "standard": {
                    "url": "https://i.ytimg.com/vi/wK3rDswPjWM/sddefault.jpg",
                    "width": 640,
                    "height": 480
                },
                "maxres": {
                    "url": "https://i.ytimg.com/vi/wK3rDswPjWM/maxresdefault.jpg",
                    "width": 1280,
                    "height": 720
                }
            },
            "channelTitle": "ER Misterios",
            "tags": [
                "essar",
                "rock",
                "caballero",
                "misterio",
                "missy bevers",
                "brandon",
                "randy",
                "bevers",
                "april sandoval",
                "bobby henry",
                "iglesia",
                "church",
                "asesinato",
                "crimen real",
                "crimen verdadero",
                "crimenes",
                "videos misteriosos",
                "casos reales",
                "paranormal",
                "caso abierto",
                "no resuelto",
                "resuelto",
                "muerte",
                "entrenadora fitness",
                "video de vigilancia",
                "camaras",
                "captado",
                "grabacion",
                "documental",
                "espa\u00f1ol",
                "asesinada en la iglesia",
                "crimen en iglesia",
                "texas",
                "2021",
                "videos paranormales",
                "videos de terror",
                "videos de misterio",
                "policial",
                "hoy",
                "actual"
            ],
            "categoryId": "24",
            "liveBroadcastContent": "none",
            "localized": {
                "title": "\u00bfQui\u00e9n MAT\u00d3 a MISSY BEVERS? REAL | EssarRock",
                "description": "Missy Bevers era instructora de fitness, alguien a quien todos amaban. Sin embargo, una ma\u00f1ana, mientras se preparaba para la clase, fue acosada y atacada. \u00bfQui\u00e9n podr\u00eda haber hecho tal cosa? Ve\u00e1moslo.\n\nSI TE GUST\u00d3 EL V\u00cdDEO NO OLVIDES APOYAR AL CANAL DEJANDO TU LIKE Y SUSCRIBIENDO, PARA AS\u00cd PODER SUBIR M\u00c1S CONTENIDO.\n\nSuscr\u00edbete\u25bahttps://www.youtube.com/channel/UCZJ8Vxj-MdzcTQ8I5yQfujg\n\n#MissyBevers #Fitness #RandyBevers"
            }
        },
        "contentDetails": {
            "duration": "PT14M27S",
            "dimension": "2d",
            "definition": "hd",
            "caption": "false",
            "licensedContent": true,
            "contentRating": {},
            "projection": "rectangular"
        },
        "status": {
            "uploadStatus": "processed",
            "privacyStatus": "public",
            "license": "youtube",
            "embeddable": true,
            "publicStatsViewable": true,
            "madeForKids": false
        },
        "statistics": {
            "viewCount": "31781",
            "likeCount": "1051",
            "favoriteCount": "0",
            "commentCount": "80"
        }
    }
]