[{"id_str":"616871075037712384","created_at":1435908499000,"full_text":"Amber Heard is bae","lang":"en","in_reply_to_status_id_str":null,"in_reply_to_user_id":null,"entities.hashtags":[],"entities.media":null,"entities.symbols":[],"entities.urls":[],"entities.user_mentions":[],"source":"<a href=\"http:\/\/twitter.com\/download\/iphone\" rel=\"nofollow\">Twitter for iPhone<\/a>","quoted_status.id_str":null,"quoted_status.created_at":null,"quoted_status.full_text":null,"quoted_status.lang":null,"quoted_status.in_reply_to_status_id_str":null,"quoted_status.in_reply_to_user_id":null,"quoted_status.entities.hashtags":null,"quoted_status.entities.media":null,"quoted_status.entities.symbols":null,"quoted_status.entities.urls":null,"quoted_status.entities.user_mentions":null,"quoted_status.user.id_str":null,"quoted_status.source":null,"user.id_str":"302841098","user.created_at":1306012154000,"user.description":"So far, so good..","user.followers_count":249,"user.friends_count":255,"user.lang":null,"user.location":"","user.name":"Jess Taylor\u2122","user.screen_name":"taylor_jess","user.profile_banner_url":"https:\/\/pbs.twimg.com\/profile_banners\/302841098\/1398881859","user.profile_image_url":"http:\/\/pbs.twimg.com\/profile_images\/1176972377307189248\/_Op4aodm_normal.jpg","user.statuses_count":8611,"user.url":null,"user.verified":false,"proc_text":"Amber Heard is bae","cluster":190},{"id_str":"616845252951937024","created_at":1435902343000,"full_text":"Amber Heard is bae \ud83d\ude0d","lang":"en","in_reply_to_status_id_str":null,"in_reply_to_user_id":null,"entities.hashtags":[],"entities.media":null,"entities.symbols":[],"entities.urls":[],"entities.user_mentions":[],"source":"<a href=\"http:\/\/twitter.com\/download\/iphone\" rel=\"nofollow\">Twitter for iPhone<\/a>","quoted_status.id_str":null,"quoted_status.created_at":null,"quoted_status.full_text":null,"quoted_status.lang":null,"quoted_status.in_reply_to_status_id_str":null,"quoted_status.in_reply_to_user_id":null,"quoted_status.entities.hashtags":null,"quoted_status.entities.media":null,"quoted_status.entities.symbols":null,"quoted_status.entities.urls":null,"quoted_status.entities.user_mentions":null,"quoted_status.user.id_str":null,"quoted_status.source":null,"user.id_str":"706034756","user.created_at":1342742568000,"user.description":"Reclaiming my time","user.followers_count":392,"user.friends_count":225,"user.lang":null,"user.location":"","user.name":"Airiana","user.screen_name":"TheHumanArrow","user.profile_banner_url":"https:\/\/pbs.twimg.com\/profile_banners\/706034756\/1617428338","user.profile_image_url":"http:\/\/pbs.twimg.com\/profile_images\/1464631706091143183\/zZdNkJuQ_normal.jpg","user.statuses_count":19697,"user.url":null,"user.verified":false,"proc_text":"Amber Heard is bae","cluster":190},{"id_str":"619602300152217600","created_at":1436559674000,"full_text":"amber heard is bae af","lang":"en","in_reply_to_status_id_str":null,"in_reply_to_user_id":null,"entities.hashtags":[],"entities.media":null,"entities.symbols":[],"entities.urls":[],"entities.user_mentions":[],"source":"<a href=\"http:\/\/twitter.com\/download\/iphone\" rel=\"nofollow\">Twitter for iPhone<\/a>","quoted_status.id_str":null,"quoted_status.created_at":null,"quoted_status.full_text":null,"quoted_status.lang":null,"quoted_status.in_reply_to_status_id_str":null,"quoted_status.in_reply_to_user_id":null,"quoted_status.entities.hashtags":null,"quoted_status.entities.media":null,"quoted_status.entities.symbols":null,"quoted_status.entities.urls":null,"quoted_status.entities.user_mentions":null,"quoted_status.user.id_str":null,"quoted_status.source":null,"user.id_str":"1608483174","user.created_at":1374335186000,"user.description":"The Netherlands | 21","user.followers_count":2618,"user.friends_count":184,"user.lang":null,"user.location":"","user.name":"Alayssa","user.screen_name":"hdrjauregui","user.profile_banner_url":"https:\/\/pbs.twimg.com\/profile_banners\/1608483174\/1513627668","user.profile_image_url":"http:\/\/pbs.twimg.com\/profile_images\/1312986701845979136\/hGpjR4pp_normal.jpg","user.statuses_count":42401,"user.url":null,"user.verified":false,"proc_text":"amber heard is bae af","cluster":190},{"id_str":"622306510756917248","created_at":1437204408000,"full_text":"Amber heard is bae af","lang":"en","in_reply_to_status_id_str":null,"in_reply_to_user_id":null,"entities.hashtags":[],"entities.media":null,"entities.symbols":[],"entities.urls":[],"entities.user_mentions":[],"source":"<a href=\"http:\/\/twitter.com\/download\/android\" rel=\"nofollow\">Twitter for Android<\/a>","quoted_status.id_str":null,"quoted_status.created_at":null,"quoted_status.full_text":null,"quoted_status.lang":null,"quoted_status.in_reply_to_status_id_str":null,"quoted_status.in_reply_to_user_id":null,"quoted_status.entities.hashtags":null,"quoted_status.entities.media":null,"quoted_status.entities.symbols":null,"quoted_status.entities.urls":null,"quoted_status.entities.user_mentions":null,"quoted_status.user.id_str":null,"quoted_status.source":null,"user.id_str":"31352118","user.created_at":1239774594000,"user.description":"floating around\u2728\u26d3\ud83d\udd2e\ud83c\udf31","user.followers_count":318,"user.friends_count":333,"user.lang":null,"user.location":"","user.name":"NALGOTICA","user.screen_name":"chingonapicosa","user.profile_banner_url":"https:\/\/pbs.twimg.com\/profile_banners\/31352118\/1609742973","user.profile_image_url":"http:\/\/pbs.twimg.com\/profile_images\/1412107710087057408\/OJ07usoR_normal.jpg","user.statuses_count":87316,"user.url":null,"user.verified":false,"proc_text":"Amber heard is bae af","cluster":190},{"id_str":"622196587981189120","created_at":1437178201000,"full_text":"Amber heard omg \ud83d\ude0d\ud83d\ude0d\ud83d\ude0d bae x2 \ud83d\ude0d","lang":"en","in_reply_to_status_id_str":null,"in_reply_to_user_id":null,"entities.hashtags":[],"entities.media":null,"entities.symbols":[],"entities.urls":[],"entities.user_mentions":[],"source":"<a href=\"http:\/\/twitter.com\/download\/android\" rel=\"nofollow\">Twitter for Android<\/a>","quoted_status.id_str":null,"quoted_status.created_at":null,"quoted_status.full_text":null,"quoted_status.lang":null,"quoted_status.in_reply_to_status_id_str":null,"quoted_status.in_reply_to_user_id":null,"quoted_status.entities.hashtags":null,"quoted_status.entities.media":null,"quoted_status.entities.symbols":null,"quoted_status.entities.urls":null,"quoted_status.entities.user_mentions":null,"quoted_status.user.id_str":null,"quoted_status.source":null,"user.id_str":"156172593","user.created_at":1276667904000,"user.description":"In the midst of movement and chaos, keep stillness inside of you. \u261c Nunquam Perit","user.followers_count":438,"user.friends_count":296,"user.lang":null,"user.location":"In my mind \ud83c\udf08","user.name":"l\u0250\u0279\u0131\u0323ss\u0250","user.screen_name":"_LARISSSAAA","user.profile_banner_url":"https:\/\/pbs.twimg.com\/profile_banners\/156172593\/1652337371","user.profile_image_url":"http:\/\/pbs.twimg.com\/profile_images\/1518121510527025153\/ypTawOPb_normal.jpg","user.statuses_count":47320,"user.url":null,"user.verified":false,"proc_text":"Amber heard omg bae x2","cluster":190},{"id_str":"616582916055920640","created_at":1435839797000,"full_text":"Amber Heard is Bae","lang":"en","in_reply_to_status_id_str":null,"in_reply_to_user_id":null,"entities.hashtags":[],"entities.media":null,"entities.symbols":[],"entities.urls":[],"entities.user_mentions":[],"source":"<a href=\"http:\/\/twitter.com\/download\/iphone\" rel=\"nofollow\">Twitter for iPhone<\/a>","quoted_status.id_str":null,"quoted_status.created_at":null,"quoted_status.full_text":null,"quoted_status.lang":null,"quoted_status.in_reply_to_status_id_str":null,"quoted_status.in_reply_to_user_id":null,"quoted_status.entities.hashtags":null,"quoted_status.entities.media":null,"quoted_status.entities.symbols":null,"quoted_status.entities.urls":null,"quoted_status.entities.user_mentions":null,"quoted_status.user.id_str":null,"quoted_status.source":null,"user.id_str":"379148259","user.created_at":1316869815000,"user.description":"\ud83d\udda4\ud83e\udd17","user.followers_count":508,"user.friends_count":576,"user.lang":null,"user.location":"Connecticut","user.name":"J","user.screen_name":"amen_jayy","user.profile_banner_url":"https:\/\/pbs.twimg.com\/profile_banners\/379148259\/1651703088","user.profile_image_url":"http:\/\/pbs.twimg.com\/profile_images\/1515016833090441227\/C6m5_1qn_normal.jpg","user.statuses_count":69705,"user.url":null,"user.verified":false,"proc_text":"Amber Heard is Bae","cluster":190},{"id_str":"619260952215691264","created_at":1436478290000,"full_text":"Amber Heard is bae \ud83d\ude0d\ud83d\ude0d\ud83d\ude0d\ud83d\ude0d","lang":"en","in_reply_to_status_id_str":null,"in_reply_to_user_id":null,"entities.hashtags":[],"entities.media":null,"entities.symbols":[],"entities.urls":[],"entities.user_mentions":[],"source":"<a href=\"http:\/\/twitter.com\/download\/iphone\" rel=\"nofollow\">Twitter for iPhone<\/a>","quoted_status.id_str":null,"quoted_status.created_at":null,"quoted_status.full_text":null,"quoted_status.lang":null,"quoted_status.in_reply_to_status_id_str":null,"quoted_status.in_reply_to_user_id":null,"quoted_status.entities.hashtags":null,"quoted_status.entities.media":null,"quoted_status.entities.symbols":null,"quoted_status.entities.urls":null,"quoted_status.entities.user_mentions":null,"quoted_status.user.id_str":null,"quoted_status.source":null,"user.id_str":"2290306446","user.created_at":1389653998000,"user.description":"22 | | IG : kaayyylla21","user.followers_count":120,"user.friends_count":100,"user.lang":null,"user.location":"Bentonville, AR","user.name":"Kayla Rivera","user.screen_name":"kaayyylla21","user.profile_banner_url":"https:\/\/pbs.twimg.com\/profile_banners\/2290306446\/1496236019","user.profile_image_url":"http:\/\/pbs.twimg.com\/profile_images\/869903025598382080\/AUPyi9bg_normal.jpg","user.statuses_count":6229,"user.url":null,"user.verified":false,"proc_text":"Amber Heard is bae","cluster":190},{"id_str":"625490697270001668","created_at":1437963577000,"full_text":"Amber Heard is bae \ud83d\ude0d","lang":"en","in_reply_to_status_id_str":null,"in_reply_to_user_id":null,"entities.hashtags":[],"entities.media":null,"entities.symbols":[],"entities.urls":[],"entities.user_mentions":[],"source":"<a href=\"http:\/\/twitter.com\/download\/android\" rel=\"nofollow\">Twitter for Android<\/a>","quoted_status.id_str":null,"quoted_status.created_at":null,"quoted_status.full_text":null,"quoted_status.lang":null,"quoted_status.in_reply_to_status_id_str":null,"quoted_status.in_reply_to_user_id":null,"quoted_status.entities.hashtags":null,"quoted_status.entities.media":null,"quoted_status.entities.symbols":null,"quoted_status.entities.urls":null,"quoted_status.entities.user_mentions":null,"quoted_status.user.id_str":null,"quoted_status.source":null,"user.id_str":"426093874","user.created_at":1322772574000,"user.description":"","user.followers_count":123,"user.friends_count":169,"user.lang":null,"user.location":"","user.name":"Shahiza \u264d\ufe0f","user.screen_name":"ForeverShahiza","user.profile_banner_url":"https:\/\/pbs.twimg.com\/profile_banners\/426093874\/1479986586","user.profile_image_url":"http:\/\/pbs.twimg.com\/profile_images\/801748178605371392\/pD0BD1dk_normal.jpg","user.statuses_count":7079,"user.url":null,"user.verified":false,"proc_text":"Amber Heard is bae","cluster":190},{"id_str":"621950712847581184","created_at":1437119579000,"full_text":"after watching Zombieland, Amber Heard is bae all day","lang":"en","in_reply_to_status_id_str":null,"in_reply_to_user_id":null,"entities.hashtags":[],"entities.media":null,"entities.symbols":[],"entities.urls":[],"entities.user_mentions":[],"source":"<a href=\"http:\/\/twitter.com\" rel=\"nofollow\">Twitter Web Client<\/a>","quoted_status.id_str":null,"quoted_status.created_at":null,"quoted_status.full_text":null,"quoted_status.lang":null,"quoted_status.in_reply_to_status_id_str":null,"quoted_status.in_reply_to_user_id":null,"quoted_status.entities.hashtags":null,"quoted_status.entities.media":null,"quoted_status.entities.symbols":null,"quoted_status.entities.urls":null,"quoted_status.entities.user_mentions":null,"quoted_status.user.id_str":null,"quoted_status.source":null,"user.id_str":"2754016893","user.created_at":1409283499000,"user.description":"figuring it out","user.followers_count":59,"user.friends_count":857,"user.lang":null,"user.location":"Houston, TX","user.name":"ice","user.screen_name":"dndrstn","user.profile_banner_url":"https:\/\/pbs.twimg.com\/profile_banners\/2754016893\/1643358785","user.profile_image_url":"http:\/\/pbs.twimg.com\/profile_images\/1487338105770319874\/bOALuZ3t_normal.jpg","user.statuses_count":2315,"user.url":null,"user.verified":false,"proc_text":"after watching Zombieland Amber Heard is bae all day","cluster":190}]