[
    {
        "kind": "youtube#video",
        "etag": "XbT1KkaO5xddINTnL8EitH6KFs8",
        "id": "l6dn3-C_pks",
        "snippet": {
            "publishedAt": "2015-07-01T15:20:15Z",
            "channelId": "UCuWeBHxVe6C69JTBpiY-Y8Q",
            "title": "FREAK BOOK: LA BIBLIA DEL FRIKISMO POR JUANITO SAY | Libro ya disponible",
            "description": "\u25ba COMPRA FREAK BOOK: http://www.tematika.com/libros/infantil_y_juvenil--18/jovenes_lectores--8/freak_book--594053.htm\n\u25ba SHOW PRESENTACION Y FIRMA DE EJEMPLARES: http://www.yenny-elateneo.com/promociones/juanito-say/\n\nMi nombre es Juan, aunque muchos me conocen como Juanito Say, o Say a secas, y les doy la bienvenida al libro que va a ser la biblia de las futuras generaciones de frikis (?), el manual esencial para todo otaku, gamer, hasta rapero, o, en su defecto, para quien quiera adentrarse en estos maravillosos mundos.\nPero, \u00bfc\u00f3mo llegu\u00e9 a escribir un libro? \u00a1Que gran pregunta! Y la verdad es que no tengo idea. Como tampoco la tengo sobre todo lo que me fue sucediendo en la vida. Simplemente trabajo duro y con toda mi energ\u00eda en lo que me hace feliz. Quiz\u00e1s ah\u00ed est\u00e9 el truco para lograr todas tus metas. Probalo.\nTe invito a ingresar en este universo fant\u00e1stico, no sin antes advertirte que es un viaje de ida, esto no tiene salida\u2026\n\n\u00a1Visita http://crunchyroll.com/freakshow y reg\u00edstrate como Premium para obtener anime GRATIS, en HD, con subtitulos y sin publicidad!\n\nSi le das like, compartes y comentas, me ayuda mucho ;)\n\u2605 SUSCRIBETE A MI CANAL: http://www.youtube.com/user/juanitosay?sub_confirmation=1\n\n\u2591\u2591\u2591\u2591\u2591\u2591\u2591\u2591\u2591\u2591\u2591\u2591\u2591\u2591\u2591\u2591\u2591\u2591\u2591\u2591\u2591\u2591\u2591\u2591\u2591\u2591\u2591\u2591\u2591\u2591\u2591\u2591\u2591\u2591\u2591\u2591\u2591\u2591\n\n\u25ba DELCARAJO ZETA - 100% DRAGON BALL: http://youtube.com/delcarajozetadb\n\u25ba MIRA FREAK SHOW EN CM, EL CANAL DE LA MUSICA, EN ARGENTINA Y PAISES LIMITROFES. SI NO TENES EL CANAL, PEDILO A TU CABLEOPERADOR.\n\n\u25ba Sigueme en:\nTwitter: http://twitter.com/juanitosay\nFacebook: http://facebook.com/juanitosayoficial\nFacebook Personal: http://facebook.com/esjuanitosay\nAsk: http://ask.fm/sayphhat\nSitio Oficial: http://mcsay.com\n\n\u25ba Contacto prensa: say@freakshowtv.com.ar\n\n\u25ba DESCARGA MI APP PARA CHROME Y FIREFOX: http://myapp.wips.com/delcarajo-teve-juanito-say-extension",
            "thumbnails": {
                "default": {
                    "url": "https://i.ytimg.com/vi/l6dn3-C_pks/default.jpg",
                    "width": 120,
                    "height": 90
                },
                "medium": {
                    "url": "https://i.ytimg.com/vi/l6dn3-C_pks/mqdefault.jpg",
                    "width": 320,
                    "height": 180
                },
                "high": {
                    "url": "https://i.ytimg.com/vi/l6dn3-C_pks/hqdefault.jpg",
                    "width": 480,
                    "height": 360
                },
                "standard": {
                    "url": "https://i.ytimg.com/vi/l6dn3-C_pks/sddefault.jpg",
                    "width": 640,
                    "height": 480
                },
                "maxres": {
                    "url": "https://i.ytimg.com/vi/l6dn3-C_pks/maxresdefault.jpg",
                    "width": 1280,
                    "height": 720
                }
            },
            "channelTitle": "DELCARAJO TV",
            "tags": [
                "freak book",
                "freakbook",
                "juanito say freak book",
                "booktuber",
                "libro youtuber",
                "libro anime",
                "anime",
                "videojuegos",
                "gamer",
                "el libro troll",
                "salseo gamer",
                "dragon ball z",
                "saint seiya",
                "mario bros",
                "friki",
                "frikismo",
                "la biblia del frikismo",
                "wigetta",
                "libros de youtubers"
            ],
            "categoryId": "24",
            "liveBroadcastContent": "none",
            "localized": {
                "title": "FREAK BOOK: LA BIBLIA DEL FRIKISMO POR JUANITO SAY | Libro ya disponible",
                "description": "\u25ba COMPRA FREAK BOOK: http://www.tematika.com/libros/infantil_y_juvenil--18/jovenes_lectores--8/freak_book--594053.htm\n\u25ba SHOW PRESENTACION Y FIRMA DE EJEMPLARES: http://www.yenny-elateneo.com/promociones/juanito-say/\n\nMi nombre es Juan, aunque muchos me conocen como Juanito Say, o Say a secas, y les doy la bienvenida al libro que va a ser la biblia de las futuras generaciones de frikis (?), el manual esencial para todo otaku, gamer, hasta rapero, o, en su defecto, para quien quiera adentrarse en estos maravillosos mundos.\nPero, \u00bfc\u00f3mo llegu\u00e9 a escribir un libro? \u00a1Que gran pregunta! Y la verdad es que no tengo idea. Como tampoco la tengo sobre todo lo que me fue sucediendo en la vida. Simplemente trabajo duro y con toda mi energ\u00eda en lo que me hace feliz. Quiz\u00e1s ah\u00ed est\u00e9 el truco para lograr todas tus metas. Probalo.\nTe invito a ingresar en este universo fant\u00e1stico, no sin antes advertirte que es un viaje de ida, esto no tiene salida\u2026\n\n\u00a1Visita http://crunchyroll.com/freakshow y reg\u00edstrate como Premium para obtener anime GRATIS, en HD, con subtitulos y sin publicidad!\n\nSi le das like, compartes y comentas, me ayuda mucho ;)\n\u2605 SUSCRIBETE A MI CANAL: http://www.youtube.com/user/juanitosay?sub_confirmation=1\n\n\u2591\u2591\u2591\u2591\u2591\u2591\u2591\u2591\u2591\u2591\u2591\u2591\u2591\u2591\u2591\u2591\u2591\u2591\u2591\u2591\u2591\u2591\u2591\u2591\u2591\u2591\u2591\u2591\u2591\u2591\u2591\u2591\u2591\u2591\u2591\u2591\u2591\u2591\n\n\u25ba DELCARAJO ZETA - 100% DRAGON BALL: http://youtube.com/delcarajozetadb\n\u25ba MIRA FREAK SHOW EN CM, EL CANAL DE LA MUSICA, EN ARGENTINA Y PAISES LIMITROFES. SI NO TENES EL CANAL, PEDILO A TU CABLEOPERADOR.\n\n\u25ba Sigueme en:\nTwitter: http://twitter.com/juanitosay\nFacebook: http://facebook.com/juanitosayoficial\nFacebook Personal: http://facebook.com/esjuanitosay\nAsk: http://ask.fm/sayphhat\nSitio Oficial: http://mcsay.com\n\n\u25ba Contacto prensa: say@freakshowtv.com.ar\n\n\u25ba DESCARGA MI APP PARA CHROME Y FIREFOX: http://myapp.wips.com/delcarajo-teve-juanito-say-extension"
            },
            "defaultAudioLanguage": "zxx"
        },
        "contentDetails": {
            "duration": "PT6M20S",
            "dimension": "2d",
            "definition": "hd",
            "caption": "false",
            "licensedContent": true,
            "contentRating": {},
            "projection": "rectangular"
        },
        "status": {
            "uploadStatus": "processed",
            "privacyStatus": "public",
            "license": "youtube",
            "embeddable": true,
            "publicStatsViewable": true,
            "madeForKids": false
        },
        "statistics": {
            "viewCount": "3170",
            "likeCount": "160",
            "favoriteCount": "0",
            "commentCount": "52"
        }
    }
]