[{"id_str":"1223854165387960320","created_at":1580624545000,"full_text":"We are with you man #JusticeForJohnnyDepp","lang":"en","in_reply_to_status_id_str":null,"in_reply_to_user_id":null,"entities.hashtags":[{"indices":[20,41],"text":"JusticeForJohnnyDepp"}],"entities.media":null,"entities.symbols":[],"entities.urls":[],"entities.user_mentions":[],"source":"<a href=\"https:\/\/mobile.twitter.com\" rel=\"nofollow\">Twitter Web App<\/a>","quoted_status.id_str":null,"quoted_status.created_at":null,"quoted_status.full_text":null,"quoted_status.lang":null,"quoted_status.in_reply_to_status_id_str":null,"quoted_status.in_reply_to_user_id":null,"quoted_status.entities.hashtags":null,"quoted_status.entities.media":null,"quoted_status.entities.symbols":null,"quoted_status.entities.urls":null,"quoted_status.entities.user_mentions":null,"quoted_status.user.id_str":null,"quoted_status.source":null,"user.id_str":"1218714835019370496","user.created_at":1579399243000,"user.description":"","user.followers_count":18,"user.friends_count":19,"user.lang":null,"user.location":"","user.name":"Aldoy","user.screen_name":"Aldwinpawl","user.profile_banner_url":"https:\/\/pbs.twimg.com\/profile_banners\/1218714835019370496\/1594013346","user.profile_image_url":"http:\/\/pbs.twimg.com\/profile_images\/1306014267519520768\/GgBMdVeJ_normal.jpg","user.statuses_count":264,"user.url":null,"user.verified":false,"proc_text":"We are with you man JusticeForJohnnyDepp","cluster":978},{"id_str":"1223902628607741954","created_at":1580636100000,"full_text":"We are all behind you. #JusticeForJohnnyDepp","lang":"en","in_reply_to_status_id_str":null,"in_reply_to_user_id":null,"entities.hashtags":[{"indices":[23,44],"text":"JusticeForJohnnyDepp"}],"entities.media":null,"entities.symbols":[],"entities.urls":[],"entities.user_mentions":[],"source":"<a href=\"http:\/\/twitter.com\/download\/android\" rel=\"nofollow\">Twitter for Android<\/a>","quoted_status.id_str":null,"quoted_status.created_at":null,"quoted_status.full_text":null,"quoted_status.lang":null,"quoted_status.in_reply_to_status_id_str":null,"quoted_status.in_reply_to_user_id":null,"quoted_status.entities.hashtags":null,"quoted_status.entities.media":null,"quoted_status.entities.symbols":null,"quoted_status.entities.urls":null,"quoted_status.entities.user_mentions":null,"quoted_status.user.id_str":null,"quoted_status.source":null,"user.id_str":"3054543691","user.created_at":1425269346000,"user.description":"twitch twitch i need a hug bitch \u2728","user.followers_count":114,"user.friends_count":110,"user.lang":null,"user.location":"Tortuga","user.name":"maki \ud83c\udf65","user.screen_name":"maclerst","user.profile_banner_url":"https:\/\/pbs.twimg.com\/profile_banners\/3054543691\/1592054607","user.profile_image_url":"http:\/\/pbs.twimg.com\/profile_images\/1268450275653640192\/Z4XSPdAk_normal.jpg","user.statuses_count":4277,"user.url":null,"user.verified":false,"proc_text":"We are all behind you JusticeForJohnnyDepp","cluster":978},{"id_str":"1223840436436922368","created_at":1580621272000,"full_text":"Jonny deppp #JusticeForJohnnyDepp","lang":"en","in_reply_to_status_id_str":null,"in_reply_to_user_id":null,"entities.hashtags":[{"indices":[12,33],"text":"JusticeForJohnnyDepp"}],"entities.media":null,"entities.symbols":[],"entities.urls":[],"entities.user_mentions":[],"source":"<a href=\"http:\/\/twitter.com\/download\/android\" rel=\"nofollow\">Twitter for Android<\/a>","quoted_status.id_str":null,"quoted_status.created_at":null,"quoted_status.full_text":null,"quoted_status.lang":null,"quoted_status.in_reply_to_status_id_str":null,"quoted_status.in_reply_to_user_id":null,"quoted_status.entities.hashtags":null,"quoted_status.entities.media":null,"quoted_status.entities.symbols":null,"quoted_status.entities.urls":null,"quoted_status.entities.user_mentions":null,"quoted_status.user.id_str":null,"quoted_status.source":null,"user.id_str":"1222752837299363840","user.created_at":1580361981000,"user.description":"asim fan","user.followers_count":17,"user.friends_count":36,"user.lang":null,"user.location":"","user.name":"Manpreet","user.screen_name":"Manpree88720593","user.profile_banner_url":null,"user.profile_image_url":"http:\/\/pbs.twimg.com\/profile_images\/1222753012508053504\/MNYXqRez_normal.jpg","user.statuses_count":1730,"user.url":null,"user.verified":false,"proc_text":"Jonny deppp JusticeForJohnnyDepp","cluster":-1},{"id_str":"1223839660763312129","created_at":1580621087000,"full_text":"We are with you man #JusticeForJohnnyDepp","lang":"en","in_reply_to_status_id_str":null,"in_reply_to_user_id":null,"entities.hashtags":[{"indices":[20,41],"text":"JusticeForJohnnyDepp"}],"entities.media":null,"entities.symbols":[],"entities.urls":[],"entities.user_mentions":[],"source":"<a href=\"http:\/\/twitter.com\/download\/android\" rel=\"nofollow\">Twitter for Android<\/a>","quoted_status.id_str":null,"quoted_status.created_at":null,"quoted_status.full_text":null,"quoted_status.lang":null,"quoted_status.in_reply_to_status_id_str":null,"quoted_status.in_reply_to_user_id":null,"quoted_status.entities.hashtags":null,"quoted_status.entities.media":null,"quoted_status.entities.symbols":null,"quoted_status.entities.urls":null,"quoted_status.entities.user_mentions":null,"quoted_status.user.id_str":null,"quoted_status.source":null,"user.id_str":"1222752837299363840","user.created_at":1580361981000,"user.description":"asim fan","user.followers_count":17,"user.friends_count":36,"user.lang":null,"user.location":"","user.name":"Manpreet","user.screen_name":"Manpree88720593","user.profile_banner_url":null,"user.profile_image_url":"http:\/\/pbs.twimg.com\/profile_images\/1222753012508053504\/MNYXqRez_normal.jpg","user.statuses_count":1730,"user.url":null,"user.verified":false,"proc_text":"We are with you man JusticeForJohnnyDepp","cluster":978},{"id_str":"1224057043797135360","created_at":1580672915000,"full_text":"@thechynnabee lol check the #JusticeForJohnnyDepp tag","lang":"en","in_reply_to_status_id_str":"1224056727462666241","in_reply_to_user_id":2535702176.0,"entities.hashtags":[{"indices":[28,49],"text":"JusticeForJohnnyDepp"}],"entities.media":null,"entities.symbols":[],"entities.urls":[],"entities.user_mentions":[{"indices":[0,13],"screen_name":"thechynnabee","id_str":"2535702176","name":"?","id":2535702176}],"source":"<a href=\"http:\/\/twitter.com\/download\/iphone\" rel=\"nofollow\">Twitter for iPhone<\/a>","quoted_status.id_str":null,"quoted_status.created_at":null,"quoted_status.full_text":null,"quoted_status.lang":null,"quoted_status.in_reply_to_status_id_str":null,"quoted_status.in_reply_to_user_id":null,"quoted_status.entities.hashtags":null,"quoted_status.entities.media":null,"quoted_status.entities.symbols":null,"quoted_status.entities.urls":null,"quoted_status.entities.user_mentions":null,"quoted_status.user.id_str":null,"quoted_status.source":null,"user.id_str":"2999781420","user.created_at":1422479576000,"user.description":"failed the vibe check | \ud83c\udded\ud83c\uddf3\ud83c\udff3\ufe0f\u200d\ud83c\udf08 | she\/they","user.followers_count":230,"user.friends_count":622,"user.lang":null,"user.location":" \u2728 boston \u2728","user.name":"childish","user.screen_name":"rayvinoooo","user.profile_banner_url":"https:\/\/pbs.twimg.com\/profile_banners\/2999781420\/1612453299","user.profile_image_url":"http:\/\/pbs.twimg.com\/profile_images\/1357353631176089601\/IkpyhCUT_normal.jpg","user.statuses_count":11266,"user.url":null,"user.verified":false,"proc_text":"thechynnabee lol check the JusticeForJohnnyDepp tag","cluster":978},{"id_str":"1223873899017928707","created_at":1580629250000,"full_text":"We are with you man! #JusticeForJohnnyDepp","lang":"en","in_reply_to_status_id_str":null,"in_reply_to_user_id":null,"entities.hashtags":[{"indices":[21,42],"text":"JusticeForJohnnyDepp"}],"entities.media":null,"entities.symbols":[],"entities.urls":[],"entities.user_mentions":[],"source":"<a href=\"http:\/\/twitter.com\/download\/android\" rel=\"nofollow\">Twitter for Android<\/a>","quoted_status.id_str":null,"quoted_status.created_at":null,"quoted_status.full_text":null,"quoted_status.lang":null,"quoted_status.in_reply_to_status_id_str":null,"quoted_status.in_reply_to_user_id":null,"quoted_status.entities.hashtags":null,"quoted_status.entities.media":null,"quoted_status.entities.symbols":null,"quoted_status.entities.urls":null,"quoted_status.entities.user_mentions":null,"quoted_status.user.id_str":null,"quoted_status.source":null,"user.id_str":"242715577","user.created_at":1295958955000,"user.description":"HIGH PERFORMANCE PC HARDWARE ADDICT\u2764\ufe0f\ud83d\udc9a\ud83d\udc99GAMING FOR A GOOD CAUSE, dealing with PC since 1998. PC MODDER, CUSTOM PC BULDS, HARDWARE ANALYST\/CONSULTANT","user.followers_count":664,"user.friends_count":2280,"user.lang":null,"user.location":"Worlds","user.name":"Omonla360|OPFYPC","user.screen_name":"i_omonla","user.profile_banner_url":"https:\/\/pbs.twimg.com\/profile_banners\/242715577\/1587410941","user.profile_image_url":"http:\/\/pbs.twimg.com\/profile_images\/1370323404545474560\/CKSAJz05_normal.jpg","user.statuses_count":17437,"user.url":"https:\/\/t.co\/XMTsErCycG","user.verified":false,"proc_text":"We are with you man JusticeForJohnnyDepp","cluster":978},{"id_str":"1223782466382548992","created_at":1580607451000,"full_text":"Finally this is happening. #JusticeForJohnnyDepp","lang":"en","in_reply_to_status_id_str":null,"in_reply_to_user_id":null,"entities.hashtags":[{"indices":[27,48],"text":"JusticeForJohnnyDepp"}],"entities.media":null,"entities.symbols":[],"entities.urls":[],"entities.user_mentions":[],"source":"<a href=\"http:\/\/twitter.com\/download\/iphone\" rel=\"nofollow\">Twitter for iPhone<\/a>","quoted_status.id_str":null,"quoted_status.created_at":null,"quoted_status.full_text":null,"quoted_status.lang":null,"quoted_status.in_reply_to_status_id_str":null,"quoted_status.in_reply_to_user_id":null,"quoted_status.entities.hashtags":null,"quoted_status.entities.media":null,"quoted_status.entities.symbols":null,"quoted_status.entities.urls":null,"quoted_status.entities.user_mentions":null,"quoted_status.user.id_str":null,"quoted_status.source":null,"user.id_str":"1178459076813963264","user.created_at":1569801529000,"user.description":"a test of my patience, there's things that we'll never know | she\u2022her\u2022pan","user.followers_count":140,"user.friends_count":165,"user.lang":null,"user.location":"Looking for Concert Tickets","user.name":"gia","user.screen_name":"caramelmacgiato","user.profile_banner_url":"https:\/\/pbs.twimg.com\/profile_banners\/1178459076813963264\/1616692328","user.profile_image_url":"http:\/\/pbs.twimg.com\/profile_images\/1351960682028097536\/jVBrvXir_normal.jpg","user.statuses_count":2630,"user.url":"https:\/\/t.co\/N4zbOi9hME","user.verified":false,"proc_text":"Finally this is happening JusticeForJohnnyDepp","cluster":978},{"id_str":"1223785054578663425","created_at":1580608068000,"full_text":"We stand with you homeboy! #JusticeForJohnnyDepp","lang":"en","in_reply_to_status_id_str":null,"in_reply_to_user_id":null,"entities.hashtags":[{"indices":[27,48],"text":"JusticeForJohnnyDepp"}],"entities.media":null,"entities.symbols":[],"entities.urls":[],"entities.user_mentions":[],"source":"<a href=\"https:\/\/mobile.twitter.com\" rel=\"nofollow\">Twitter Web App<\/a>","quoted_status.id_str":null,"quoted_status.created_at":null,"quoted_status.full_text":null,"quoted_status.lang":null,"quoted_status.in_reply_to_status_id_str":null,"quoted_status.in_reply_to_user_id":null,"quoted_status.entities.hashtags":null,"quoted_status.entities.media":null,"quoted_status.entities.symbols":null,"quoted_status.entities.urls":null,"quoted_status.entities.user_mentions":null,"quoted_status.user.id_str":null,"quoted_status.source":null,"user.id_str":"1223616211654729730","user.created_at":1580567822000,"user.description":"he\/him or they\/them \ud83c\udde9\ud83c\uddea  \ndigital artist + oc design \/\/ goth \/\/ 27\ndemi-panromantic\/ace\n\n\ud83d\udcab art tag: #g0ddraws \ncoms always open! https:\/\/t.co\/359gfsfqZU","user.followers_count":138,"user.friends_count":92,"user.lang":null,"user.location":"","user.name":"Golden Ghost \ud83d\udcab\ud83d\udc80","user.screen_name":"g0dp4rticl3","user.profile_banner_url":"https:\/\/pbs.twimg.com\/profile_banners\/1223616211654729730\/1610848195","user.profile_image_url":"http:\/\/pbs.twimg.com\/profile_images\/1380067502487699458\/m5yY_dDC_normal.jpg","user.statuses_count":2633,"user.url":null,"user.verified":false,"proc_text":"We stand with you homeboy JusticeForJohnnyDepp","cluster":978},{"id_str":"1223781814499598341","created_at":1580607296000,"full_text":"No matter how beautiful you are by face,if you aren\u2019t good human by heart its useless #AmberHeard #JusticeForJohnnyDepp","lang":"en","in_reply_to_status_id_str":null,"in_reply_to_user_id":null,"entities.hashtags":[{"indices":[86,97],"text":"AmberHeard"},{"indices":[98,119],"text":"JusticeForJohnnyDepp"}],"entities.media":null,"entities.symbols":[],"entities.urls":[],"entities.user_mentions":[],"source":"<a href=\"http:\/\/twitter.com\/download\/iphone\" rel=\"nofollow\">Twitter for iPhone<\/a>","quoted_status.id_str":null,"quoted_status.created_at":null,"quoted_status.full_text":null,"quoted_status.lang":null,"quoted_status.in_reply_to_status_id_str":null,"quoted_status.in_reply_to_user_id":null,"quoted_status.entities.hashtags":null,"quoted_status.entities.media":null,"quoted_status.entities.symbols":null,"quoted_status.entities.urls":null,"quoted_status.entities.user_mentions":null,"quoted_status.user.id_str":null,"quoted_status.source":null,"user.id_str":"376810671","user.created_at":1316530094000,"user.description":"Don\u2019t consider my kindness as my weakness,the beast inside me is sleeping not dead","user.followers_count":29,"user.friends_count":104,"user.lang":null,"user.location":"Selangor, Malaysia","user.name":"money singh \u2665\ufe0f","user.screen_name":"mani3450","user.profile_banner_url":"https:\/\/pbs.twimg.com\/profile_banners\/376810671\/1578739966","user.profile_image_url":"http:\/\/pbs.twimg.com\/profile_images\/1215949220273774593\/TP6-NdFP_normal.jpg","user.statuses_count":2087,"user.url":null,"user.verified":false,"proc_text":"No matter how beautiful you are by face if you aren t good human by heart its useless AmberHeard JusticeForJohnnyDepp","cluster":-1},{"id_str":"1223781162130100224","created_at":1580607140000,"full_text":"We are with you  #JusticeForJohnnyDepp","lang":"en","in_reply_to_status_id_str":null,"in_reply_to_user_id":null,"entities.hashtags":[{"indices":[17,38],"text":"JusticeForJohnnyDepp"}],"entities.media":null,"entities.symbols":[],"entities.urls":[],"entities.user_mentions":[],"source":"<a href=\"http:\/\/twitter.com\/download\/iphone\" rel=\"nofollow\">Twitter for iPhone<\/a>","quoted_status.id_str":null,"quoted_status.created_at":null,"quoted_status.full_text":null,"quoted_status.lang":null,"quoted_status.in_reply_to_status_id_str":null,"quoted_status.in_reply_to_user_id":null,"quoted_status.entities.hashtags":null,"quoted_status.entities.media":null,"quoted_status.entities.symbols":null,"quoted_status.entities.urls":null,"quoted_status.entities.user_mentions":null,"quoted_status.user.id_str":null,"quoted_status.source":null,"user.id_str":"376810671","user.created_at":1316530094000,"user.description":"Don\u2019t consider my kindness as my weakness,the beast inside me is sleeping not dead","user.followers_count":29,"user.friends_count":104,"user.lang":null,"user.location":"Selangor, Malaysia","user.name":"money singh \u2665\ufe0f","user.screen_name":"mani3450","user.profile_banner_url":"https:\/\/pbs.twimg.com\/profile_banners\/376810671\/1578739966","user.profile_image_url":"http:\/\/pbs.twimg.com\/profile_images\/1215949220273774593\/TP6-NdFP_normal.jpg","user.statuses_count":2087,"user.url":null,"user.verified":false,"proc_text":"We are with you JusticeForJohnnyDepp","cluster":978},{"id_str":"1224019264274944001","created_at":1580663908000,"full_text":"@rizickyusuph1 I follow back asap @mwea_king\n#JusticeForJohnnyDepp","lang":"en","in_reply_to_status_id_str":"1224018494980874240","in_reply_to_user_id":8.045385033e+17,"entities.hashtags":[{"indices":[45,66],"text":"JusticeForJohnnyDepp"}],"entities.media":null,"entities.symbols":[],"entities.urls":[],"entities.user_mentions":[{"indices":[0,14],"screen_name":"rizickyusuph1","id_str":"804538503333814273","name":"\u26a1FOLLOW HELP\u26a1","id":804538503333814273}],"source":"<a href=\"http:\/\/twitter.com\/download\/android\" rel=\"nofollow\">Twitter for Android<\/a>","quoted_status.id_str":null,"quoted_status.created_at":null,"quoted_status.full_text":null,"quoted_status.lang":null,"quoted_status.in_reply_to_status_id_str":null,"quoted_status.in_reply_to_user_id":null,"quoted_status.entities.hashtags":null,"quoted_status.entities.media":null,"quoted_status.entities.symbols":null,"quoted_status.entities.urls":null,"quoted_status.entities.user_mentions":null,"quoted_status.user.id_str":null,"quoted_status.source":null,"user.id_str":"1088176151418359808","user.created_at":1548276386000,"user.description":"Inspire a generation","user.followers_count":3543,"user.friends_count":3627,"user.lang":null,"user.location":"Nairobi, Kenya","user.name":"Mwea King","user.screen_name":"mweaking001","user.profile_banner_url":"https:\/\/pbs.twimg.com\/profile_banners\/1088176151418359808\/1605931468","user.profile_image_url":"http:\/\/pbs.twimg.com\/profile_images\/1372248476298444801\/cltJ9b0i_normal.jpg","user.statuses_count":3307,"user.url":null,"user.verified":false,"proc_text":"rizickyusuph1 I follow back asap mwea_king JusticeForJohnnyDepp","cluster":978},{"id_str":"1223974350044397568","created_at":1580653200000,"full_text":"We are with you man\n#JusticeForJohnnyDepp","lang":"en","in_reply_to_status_id_str":null,"in_reply_to_user_id":null,"entities.hashtags":[{"indices":[20,41],"text":"JusticeForJohnnyDepp"}],"entities.media":null,"entities.symbols":[],"entities.urls":[],"entities.user_mentions":[],"source":"<a href=\"https:\/\/mobile.twitter.com\" rel=\"nofollow\">Twitter Web App<\/a>","quoted_status.id_str":null,"quoted_status.created_at":null,"quoted_status.full_text":null,"quoted_status.lang":null,"quoted_status.in_reply_to_status_id_str":null,"quoted_status.in_reply_to_user_id":null,"quoted_status.entities.hashtags":null,"quoted_status.entities.media":null,"quoted_status.entities.symbols":null,"quoted_status.entities.urls":null,"quoted_status.entities.user_mentions":null,"quoted_status.user.id_str":null,"quoted_status.source":null,"user.id_str":"178833117","user.created_at":1281904462000,"user.description":"\u00abLa vida es s\u00f3lo la expresi\u00f3n extrema de la qu\u00edmica compleja.\u00bb","user.followers_count":568,"user.friends_count":853,"user.lang":null,"user.location":"El Salvador, San Salvador","user.name":"Ricardo Manzur","user.screen_name":"casaselsalvador","user.profile_banner_url":"https:\/\/pbs.twimg.com\/profile_banners\/178833117\/1575332540","user.profile_image_url":"http:\/\/pbs.twimg.com\/profile_images\/1305358457047003136\/vLt9Cvei_normal.jpg","user.statuses_count":15343,"user.url":"https:\/\/t.co\/g38RGAjVWG","user.verified":false,"proc_text":"We are with you man JusticeForJohnnyDepp","cluster":978}]